pyhydrophone/__init__.py
pyhydrophone/amar.py
pyhydrophone/bruelkjaer.py
pyhydrophone/ears.py
pyhydrophone/hydrophone.py
pyhydrophone/icListen.py
pyhydrophone/mte.py
pyhydrophone/rtsys.py
pyhydrophone/soundtrap.py
pyhydrophone/uaural.py
pyhydrophone/upam.py
pyhydrophone-0.3.1.dist-info/LICENSE
pyhydrophone-0.3.1.dist-info/METADATA
pyhydrophone-0.3.1.dist-info/WHEEL
pyhydrophone-0.3.1.dist-info/RECORD
