Metadata-Version: 2.1
Name: pyhydrophone
Version: 0.3.1
Summary: python package to read and calibrate hydrophone data
License: OSI Approved :: MIT License
Author: Clea Parcerisas
Author-email: clea.parcerisas@vliz.be
Requires-Python: >=3.9,<3.13.0
Classifier: License :: Other/Proprietary License
Classifier: Programming Language :: Python :: 3
Classifier: Programming Language :: Python :: 3.9
Classifier: Programming Language :: Python :: 3.10
Classifier: Programming Language :: Python :: 3.11
Classifier: Programming Language :: Python :: 3.12
Requires-Dist: openpyxl (>=3.1.2,<4.0.0)
Requires-Dist: pandas (>=2.0.2,<3.0.0)
Requires-Dist: requests (>=2.31.0,<3.0.0)
Requires-Dist: scipy (==1.13.1)
Requires-Dist: soundfile (>=0.12.1,<0.13.0)
